airflow_duckdb/__init__.py
airflow_duckdb/operators/__init__.py
airflow_duckdb/operators/duckdb.py
airflow_duckdb-0.1.2.dist-info/LICENSE
airflow_duckdb-0.1.2.dist-info/METADATA
airflow_duckdb-0.1.2.dist-info/WHEEL
airflow_duckdb-0.1.2.dist-info/RECORD
