Metadata-Version: 2.1
Name: airflow-duckdb
Version: 0.1.2
Summary: A package to run DuckDB queries from Apache Airflow
Home-page: https://github.com/hussein-awala/airflow-duckdb
License: Apache-2.0
Keywords: airflow,duckdb,kubernetes,airflow-duckdb
Author: Hussein Awala
Author-email: hussein@awala.fr
Requires-Python: >=3.8,<3.12
Classifier: License :: OSI Approved :: Apache Software License
Classifier: Programming Language :: Python :: 3
Classifier: Programming Language :: Python :: 3.8
Classifier: Programming Language :: Python :: 3.9
Classifier: Programming Language :: Python :: 3.10
Classifier: Programming Language :: Python :: 3.11
Requires-Dist: apache-airflow (>=2.6.0,<3.0.0)
Requires-Dist: apache-airflow-providers-cncf-kubernetes (>=7.0.0,<8.0.0)
Requires-Dist: sqlparse (>=0.4.4,<0.5.0)
Project-URL: Bug Tracker, https://github.com/hussein-awala/airflow-duckdb/issues
Project-URL: Documentation, https://github.com/hussein-awala/airflow-duckdb/blob/main/README.md
Project-URL: Repository, https://github.com/hussein-awala/airflow-duckdb
